httpdbg/__init__.py
httpdbg/__main__.py
httpdbg/args.py
httpdbg/env.py
httpdbg/exception.py
httpdbg/export.py
httpdbg/http_status_code.py
httpdbg/initiator.py
httpdbg/log.py
httpdbg/mode_console.py
httpdbg/mode_module.py
httpdbg/mode_script.py
httpdbg/preview.py
httpdbg/records.py
httpdbg/server.py
httpdbg/utils.py
httpdbg/hooks/__init__.py
httpdbg/hooks/aiohttp.py
httpdbg/hooks/all.py
httpdbg/hooks/external.py
httpdbg/hooks/fastapi.py
httpdbg/hooks/flask.py
httpdbg/hooks/generic.py
httpdbg/hooks/h2.py
httpdbg/hooks/http.py
httpdbg/hooks/httpx.py
httpdbg/hooks/pytest.py
httpdbg/hooks/record.py
httpdbg/hooks/recordhttp1.py
httpdbg/hooks/recordhttp2.py
httpdbg/hooks/requests.py
httpdbg/hooks/socket.py
httpdbg/hooks/starlette.py
httpdbg/hooks/template_sitecustomize.py
httpdbg/hooks/unittest.py
httpdbg/hooks/urllib3.py
httpdbg/hooks/utils.py
httpdbg/hooks/uvicorn.py
httpdbg/webapp/__init__.py
httpdbg/webapp/api.py
httpdbg/webapp/app.py
httpdbg/webapp/static/api.js
httpdbg/webapp/static/column.css
httpdbg/webapp/static/configuration.css
httpdbg/webapp/static/configuration.js
httpdbg/webapp/static/detail.css
httpdbg/webapp/static/favicon.ico
httpdbg/webapp/static/filter.js
httpdbg/webapp/static/index.htm
httpdbg/webapp/static/main.js
httpdbg/webapp/static/mustache.min.js
httpdbg/webapp/static/render.js
httpdbg/webapp/static/style.css
httpdbg/webapp/static/table.css
httpdbg/webapp/static/icons/chevron-direction-top-outline-icon.svg
httpdbg/webapp/static/icons/download-install-line-icon.svg
httpdbg/webapp/static/icons/engine-gears-icon.svg
httpdbg/webapp/static/icons/eye-blind-icon.svg
httpdbg/webapp/static/icons/eye-icon.svg
httpdbg/webapp/static/icons/files-papers-outline-icon.svg
httpdbg/webapp/static/icons/filter-outline-icon.svg
httpdbg/webapp/static/icons/lock-line-icon.svg
httpdbg/webapp/static/icons/lock-open-line-icon.svg
httpdbg/webapp/static/icons/math-multiplication-icon.svg
httpdbg/webapp/static/icons/push-pin-green-icon.svg
httpdbg-2.1.4.dist-info/licenses/LICENSE
httpdbg-2.1.4.dist-info/METADATA
httpdbg-2.1.4.dist-info/WHEEL
httpdbg-2.1.4.dist-info/entry_points.txt
httpdbg-2.1.4.dist-info/top_level.txt
httpdbg-2.1.4.dist-info/RECORD
