Metadata-Version: 2.4
Name: httpdbg
Version: 2.1.4
Summary: A very simple tool to debug HTTP(S) client and server requests.
Author-email: cle-b <cle@tictac.pm>
License: Apache-2.0
Project-URL: Source, https://github.com/cle-b/httpdbg/
Project-URL: Documentation, https://httpdbg.readthedocs.io/
Classifier: Development Status :: 5 - Production/Stable
Classifier: Intended Audience :: Developers
Classifier: License :: OSI Approved :: Apache Software License
Classifier: Operating System :: OS Independent
Classifier: Programming Language :: Python :: 3
Classifier: Programming Language :: Python :: 3.9
Classifier: Programming Language :: Python :: 3.10
Classifier: Programming Language :: Python :: 3.11
Classifier: Programming Language :: Python :: 3.12
Classifier: Programming Language :: Python :: 3.13
Classifier: Topic :: Internet :: WWW/HTTP
Classifier: Topic :: Software Development :: Testing
Classifier: Topic :: Utilities
Requires-Python: >=3.9
License-File: LICENSE
Dynamic: license-file
